matrix_roomba/__init__.py
matrix_roomba/bot.py
matrix_roomba-0.1.4.dist-info/METADATA
matrix_roomba-0.1.4.dist-info/WHEEL
matrix_roomba-0.1.4.dist-info/entry_points.txt
matrix_roomba-0.1.4.dist-info/licenses/LICENSE
matrix_roomba-0.1.4.dist-info/RECORD
