Metadata-Version: 2.4
Name: matrix-roomba
Version: 0.1.4
Summary: A Matrix bot that helps you shut down rooms
Project-URL: Homepage, https://git.private.coffee/PrivateCoffee/matrix-roomba
Project-URL: Bug Tracker, https://git.private.coffee/PrivateCoffee/matrix-roomba/issues
Author-email: "Private.coffee Team" <support@private.coffee>
License: Copyright (c) 2024 Private.coffee Team <support@private.coffee>
License-File: LICENSE
Classifier: License :: OSI Approved :: MIT License
Classifier: Operating System :: OS Independent
Classifier: Programming Language :: Python :: 3
Requires-Python: >=3.10
Requires-Dist: matrix-nio
Requires-Dist: pyyaml
